hcapy/__init__.py
hcapy/GeoServer/GeoServer.py
hcapy/GeoServer/__init__.py
hcapy/common/__init__.py
hcapy/common/clear_env.py
hcapy/common/print_jindu.py
hcapy/file/Basic.py
hcapy/file/CAD.py
hcapy/file/SHP.py
hcapy/file/TIFF.py
hcapy/file/ZIP.py
hcapy/file/__init__.py
hcapy/geospatial/Converter.py
hcapy/geospatial/__init__.py
hcapy/geospatial/geojson.py
hcapy-1.8.dist-info/LICENSE
hcapy-1.8.dist-info/METADATA
hcapy-1.8.dist-info/WHEEL
hcapy-1.8.dist-info/top_level.txt
hcapy-1.8.dist-info/RECORD
